qbud/__init__.py
qbud/_client.py
qbud/_constants.py
qbud/_exceptions.py
qbud/assistant.py
qbud/chat.py
qbud-0.1.1.dist-info/METADATA
qbud-0.1.1.dist-info/WHEEL
qbud-0.1.1.dist-info/licenses/LICENSE
qbud-0.1.1.dist-info/RECORD
