Metadata-Version: 2.3
Name: qbud
Version: 0.1.1
Summary: A package for managing qBud assistants and chats
Project-URL: Homepage, https://github.com/justus-qbud/qbud-client-python
Project-URL: Bug Tracker, https://github.com/justus-qbud/qbud-client-python/issues
Author-email: Justus Katerberg <j.katerberg@qbud.nl>
License-File: LICENSE
Classifier: License :: OSI Approved :: MIT License
Classifier: Operating System :: OS Independent
Classifier: Programming Language :: Python :: 3
Requires-Python: >=3.9
Requires-Dist: requests~=2.32.3
